MANIFEST.in
README.rst
requirements.txt
setup.cfg
setup.py
test-requirements.txt
hitbtcapi/__init__.py
hitbtcapi/client.py
hitbtcapi/compat.py
hitbtcapi/errors.py
hitbtcapi/utils.py
hitbtcapi.egg-info/PKG-INFO
hitbtcapi.egg-info/SOURCES.txt
hitbtcapi.egg-info/dependency_links.txt
hitbtcapi.egg-info/requires.txt
hitbtcapi.egg-info/top_level.txt
tests/__init__.py
tests/test_client.py
tests/test_utils.py