Metadata-Version: 1.1
Name: hitbtcapi
Version: 1.1.1
Summary: HitBTC API Client library
Home-page: https://github.com/pulkit1991/hitbtcapi
Author: Pulkit Gupta
Author-email: gupta.pulkit91@gmail.com
License: MIT
Download-URL: https://github.com/pulkit1991/hitbtcapi/tarball/1.1.1
Keywords: hitbtc,api,client,bitcoin,altcoin,trading
Platform: UNKNOWN
Classifier: Intended Audience :: Developers
Classifier: License :: OSI Approved :: MIT License
Classifier: Operating System :: OS Independent
Classifier: Programming Language :: Python :: 2
Classifier: Programming Language :: Python :: 2.7
Classifier: Programming Language :: Python :: 3.4
Classifier: Programming Language :: Python :: 3.5
Classifier: Programming Language :: Python :: 3.6
Classifier: Programming Language :: Python
Classifier: Topic :: Software Development :: Libraries :: Python Modules
